tianhutools/__init__.py
tianhutools/ip.py
tianhutools/jiami.py
tianhutools/text.py
tianhutools-1.0.3.dist-info/METADATA
tianhutools-1.0.3.dist-info/WHEEL
tianhutools-1.0.3.dist-info/top_level.txt
tianhutools-1.0.3.dist-info/RECORD
