Metadata-Version: 2.1
Name: tianhutools
Version: 1.0.3
Summary: 由天狐宗开发的工具，方便开发时使用,已更名为tianhutools
Home-page: https://github.com/tianhuzong/thztools
Author: Sen
Author-email: tianhuzong@qq.com
License: MIT
Classifier: Programming Language :: Python :: 3
Classifier: License :: OSI Approved :: MIT License
Classifier: Operating System :: OS Independent
Requires-Dist: rsa
Requires-Dist: cryptography
Requires-Dist: 2ip
Requires-Dist: sumy
Requires-Dist: jieba
